spacefrontiers/__init__.py
spacefrontiers/clients/__init__.py
spacefrontiers/clients/_ai_api_client.py
spacefrontiers/clients/_search_api_client.py
spacefrontiers/clients/_store_api_client.py
spacefrontiers/clients/build_protos.sh
spacefrontiers/clients/protos/__init__.py
spacefrontiers/clients/protos/service.proto
spacefrontiers/clients/protos/service_pb2.py
spacefrontiers/clients/protos/service_pb2.pyi
spacefrontiers/clients/protos/service_pb2_grpc.py
spacefrontiers/clients/types/__init__.py
spacefrontiers_clients-0.0.113.dist-info/METADATA
spacefrontiers_clients-0.0.113.dist-info/WHEEL
spacefrontiers_clients-0.0.113.dist-info/RECORD
