Metadata-Version: 2.4
Name: spacefrontiers-clients
Version: 0.0.113
Summary: Add your description here
Requires-Python: >=3.9
Requires-Dist: aiobaseclient
Requires-Dist: aiogrpcclient>=1.3.20
Requires-Dist: grpcio>=1.71.0
Requires-Dist: izihawa-textutils
Requires-Dist: pydantic>=2.10.6
Requires-Dist: tenacity>=9.0.0
